ADVANCE/Advance.py
ADVANCE/__init__.py
ADVANCE/py.typed
AIRA_MX_1/Colors.py
AIRA_MX_1/ControlElementUtils.py
AIRA_MX_1/NotifyingMixerComponent.py
AIRA_MX_1/NotifyingSessionComponent.py
AIRA_MX_1/RolandMX1.py
AIRA_MX_1/SkinDefault.py
AIRA_MX_1/__init__.py
AIRA_MX_1/py.typed
APC20/APC20.py
APC20/BackgroundComponent.py
APC20/ShiftableSelectorComponent.py
APC20/ShiftableZoomingComponent.py
APC20/SliderModesComponent.py
APC20/__init__.py
APC20/consts.py
APC20/py.typed
APC40/APC40.py
APC40/SessionComponent.py
APC40/TransportComponent.py
APC40/__init__.py
APC40/py.typed
APC40_MkII/APC40_MkII.py
APC40_MkII/BankToggleComponent.py
APC40_MkII/Colors.py
APC40_MkII/MixerComponent.py
APC40_MkII/QuantizationComponent.py
APC40_MkII/TransportComponent.py
APC40_MkII/__init__.py
APC40_MkII/py.typed
APC64/__init__.py
APC64/colors.py
APC64/device.py
APC64/display.py
APC64/elements.py
APC64/firmware_mode.py
APC64/global_quantization.py
APC64/mappings.py
APC64/midi.py
APC64/mixer.py
APC64/py.typed
APC64/recording.py
APC64/render_to_clip.py
APC64/session.py
APC64/settings.py
APC64/skin.py
APC64/touch_strip.py
APC64/transport.py
APC_Key_25/APC_Key_25.py
APC_Key_25/MixerComponent.py
APC_Key_25/SendToggleComponent.py
APC_Key_25/__init__.py
APC_Key_25/py.typed
APC_Key_25_mk2/__init__.py
APC_Key_25_mk2/colors.py
APC_Key_25_mk2/elements.py
APC_Key_25_mk2/mappings.py
APC_Key_25_mk2/py.typed
APC_mini/APC_mini.py
APC_mini/__init__.py
APC_mini/py.typed
APC_mini_mk2/__init__.py
APC_mini_mk2/colors.py
APC_mini_mk2/elements.py
APC_mini_mk2/mappings.py
APC_mini_mk2/py.typed
ATOM/__init__.py
ATOM/colors.py
ATOM/drum_group.py
ATOM/elements.py
ATOM/keyboard.py
ATOM/mappings.py
ATOM/midi.py
ATOM/note_pad.py
ATOM/py.typed
ATOM/skin.py
ATOMSQ/__init__.py
ATOMSQ/colors.py
ATOMSQ/display.py
ATOMSQ/elements.py
ATOMSQ/launch_and_stop.py
ATOMSQ/mappings.py
ATOMSQ/midi.py
ATOMSQ/py.typed
ATOMSQ/skin.py
ATOMSQ/touch_strip.py
Akai_Force_MPC/__init__.py
Akai_Force_MPC/akai_force_mpc.py
Akai_Force_MPC/background.py
ableton_control_surface_scripts-0.0.7.dist-info/METADATA
ableton_control_surface_scripts-0.0.7.dist-info/WHEEL
ableton_control_surface_scripts-0.0.7.dist-info/py.typed
ableton_control_surface_scripts-0.0.7.dist-info/top_level.txt
ableton_control_surface_scripts-0.0.7.dist-info/RECORD
